alembic_set_date_trigger_plugin/__init__.py
alembic_set_date_trigger_plugin/function_op.py
alembic_set_date_trigger_plugin/sqlalchemy_types.py
alembic_set_date_trigger_plugin/trigger_op.py
alembic_set_date_trigger_plugin-0.0.5.dist-info/LICENSE
alembic_set_date_trigger_plugin-0.0.5.dist-info/METADATA
alembic_set_date_trigger_plugin-0.0.5.dist-info/WHEEL
alembic_set_date_trigger_plugin-0.0.5.dist-info/top_level.txt
alembic_set_date_trigger_plugin-0.0.5.dist-info/RECORD
